{
  "to": "gestion@limbour.ca",
  "clinicName": "Centre Dentaire Limbour",
  "subject": "Centre Dentaire Limbour — last note",
  "body": "Bonjour,\n\nOne last note before I close this out.\n\nI came across a review from a patient mentioning that the dentist was running late with no communication about the wait. That specific gap — keeping patients informed when things don't go as scheduled — is exactly the kind of thing I help fix.\n\nWhat I'd set up for Centre Dentaire Limbour: automated appointment reminders at 72h and 24h before each visit, missed call follow-up so no caller goes unanswered, and a reactivation campaign for patients you haven't seen in 12+ months.\n\n5-day setup. Split payment — you see it working before paying the second half. No monthly fees.\n\nIf the timing isn't right, completely understood. If it ever becomes useful, just reply.\n\nMohamed\nClinicFlow Automation\ncontact@clinicflowautomation.com\n438-544-0442\n\n---\nTo opt out of future emails, reply with 'unsubscribe'.\nClinicFlow Automation · Montreal, QC · Canada",
  "sent": true,
  "sentAt": "2026-05-10T13:45:04.004Z"
}