{
	"id": "kSG9RbtrRhfR7w3",
	"json": "{\"id\":\"kSG9RbtrRhfR7w3\",\"url\":\"https://wordpress.org/plugins/search/chatbot/page/1/\",\"loadedUrl\":\"https://wordpress.org/plugins/search/chatbot/page/1/\",\"uniqueKey\":\"https://wordpress.org/plugins/search/chatbot/page/1\",\"method\":\"GET\",\"noRetry\":false,\"retryCount\":0,\"errorMessages\":[],\"headers\":{},\"userData\":{\"kind\":\"search\",\"kw\":\"chatbot\",\"__crawlee\":{\"state\":4}},\"handledAt\":\"2026-06-23T12:02:54.459Z\"}",
	"method": "GET",
	"orderNo": null,
	"retryCount": 0,
	"uniqueKey": "https://wordpress.org/plugins/search/chatbot/page/1",
	"url": "https://wordpress.org/plugins/search/chatbot/page/1/"
}